LICENSE
gadd/__init__.py
gadd/conf.py
gadd/gadd.py
gadd-0.2.3.dist-info/entry_points.txt
gadd-0.2.3.dist-info/LICENSE
gadd-0.2.3.dist-info/WHEEL
gadd-0.2.3.dist-info/METADATA
gadd-0.2.3.dist-info/RECORD
